[
  {
    "firstName": "John",
    "lastName": "Doe",
    "phoneNumber": "1234567890",
    "shippingAddress": "123 Main St, City, Country",
    "billingAddress": "456 Elm St, City, Country",
    "password": "hashed_password_here"
  },
  {
    "firstName": "Jane",
    "lastName": "Doe",
    "phoneNumber": "0987654321",
    "shippingAddress": "456 Oak St, City, Country",
    "billingAddress": "789 Maple St, City, Country",
    "password": "hashed_password_here"
  },
  {
    "firstName": "Alice",
    "lastName": "Smith",
    "phoneNumber": "2345678901",
    "shippingAddress": "789 Elm St, City, Country",
    "billingAddress": "123 Pine St, City, Country",
    "password": "hashed_password_here"
  },
  {
    "firstName": "Bob",
    "lastName": "Johnson",
    "phoneNumber": "6789012345",
    "shippingAddress": "456 Birch St, City, Country",
    "billingAddress": "789 Cedar St, City, Country",
    "password": "hashed_password_here"
  },
  {
    "firstName": "Emily",
    "lastName": "Williams",
    "phoneNumber": "3456789012",
    "shippingAddress": "123 Elm St, City, Country",
    "billingAddress": "456 Oak St, City, Country",
    "password": "hashed_password_here"
  },
  {
    "firstName": "Michael",
    "lastName": "Brown",
    "phoneNumber": "7890123456",
    "shippingAddress": "789 Maple St, City, Country",
    "billingAddress": "123 Pine St, City, Country",
    "password": "hashed_password_here"
  },
  {
    "firstName": "Emma",
    "lastName": "Jones",
    "phoneNumber": "4567890123",
    "shippingAddress": "456 Oak St, City, Country",
    "billingAddress": "789 Elm St, City, Country",
    "password": "hashed_password_here"
  },
  {
    "firstName": "James",
    "lastName": "Garcia",
    "phoneNumber": "8901234567",
    "shippingAddress": "789 Cedar St, City, Country",
    "billingAddress": "123 Birch St, City, Country",
    "password": "hashed_password_here"
  },
  {
    "firstName": "Olivia",
    "lastName": "Martinez",
    "phoneNumber": "5678901234",
    "shippingAddress": "123 Main St, City, Country",
    "billingAddress": "456 Elm St, City, Country",
    "password": "hashed_password_here"
  },
  {
    "firstName": "William",
    "lastName": "Hernandez",
    "phoneNumber": "9012345678",
    "shippingAddress": "456 Oak St, City, Country",
    "billingAddress": "789 Maple St, City, Country",
    "password": "hashed_password_here"
  },
  {
    "firstName": "Sophia",
    "lastName": "Lopez",
    "phoneNumber": "6789012345",
    "shippingAddress": "789 Elm St, City, Country",
    "billingAddress": "123 Pine St, City, Country",
    "password": "hashed_password_here"
  },
  {
    "firstName": "Liam",
    "lastName": "Gonzalez",
    "phoneNumber": "3456789012",
    "shippingAddress": "123 Elm St, City, Country",
    "billingAddress": "456 Oak St, City, Country",
    "password": "hashed_password_here"
  },
  {
    "firstName": "Isabella",
    "lastName": "Rodriguez",
    "phoneNumber": "8901234567",
    "shippingAddress": "789 Maple St, City, Country",
    "billingAddress": "123 Pine St, City, Country",
    "password": "hashed_password_here"
  },
  {
    "firstName": "Mason",
    "lastName": "Perez",
    "phoneNumber": "4567890123",
    "shippingAddress": "456 Oak St, City, Country",
    "billingAddress": "789 Elm St, City, Country",
    "password": "hashed_password_here"
  },
  {
    "firstName": "Charlotte",
    "lastName": "Williams",
    "phoneNumber": "9012345678",
    "shippingAddress": "789 Cedar St, City, Country",
    "billingAddress": "123 Birch St, City, Country",
    "password": "hashed_password_here"
  },
  {
    "firstName": "Logan",
    "lastName": "Flores",
    "phoneNumber": "5678901234",
    "shippingAddress": "123 Main St, City, Country",
    "billingAddress": "456 Elm St, City, Country",
    "password": "hashed_password_here"
  },
  {
    "firstName": "Amelia",
    "lastName": "Ortiz",
    "phoneNumber": "8901234567",
    "shippingAddress": "456 Oak St, City, Country",
    "billingAddress": "789 Maple St, City, Country",
    "password": "hashed_password_here"
  },
  {
    "firstName": "Ethan",
    "lastName": "Jackson",
    "phoneNumber": "3456789012",
    "shippingAddress": "789 Elm St, City, Country",
    "billingAddress": "123 Pine St, City, Country",
    "password": "hashed_password_here"
  },
  {
    "firstName": "Ava",
    "lastName": "Hill",
    "phoneNumber": "6789012345",
    "shippingAddress": "123 Elm St, City, Country",
    "billingAddress": "456 Oak St, City, Country",
    "password": "hashed_password_here"
  },
  {
    "firstName": "Noah",
    "lastName": "King",
    "phoneNumber": "9012345678",
    "shippingAddress": "789 Maple St, City, Country",
    "billingAddress": "123 Pine St, City, Country",
    "password": "hashed_password_here"
  },
  {
    "firstName": "Harper",
    "lastName": "Scott",
    "phoneNumber": "4567890123",
    "shippingAddress": "456 Oak St, City, Country",
    "billingAddress": "789 Elm St, City, Country",
    "password": "hashed_password_here"
  },
  {
    "firstName": "Lucas",
    "lastName": "Green",
    "phoneNumber": "8901234567",
    "shippingAddress": "789 Cedar St, City, Country",
    "billingAddress": "123 Birch St, City, Country",
    "password": "hashed_password_here"
  },
  {
    "firstName": "Evelyn",
    "lastName": "Adams",
    "phoneNumber": "5678901234",
    "shippingAddress": "123 Main St, City, Country",
    "billingAddress": "456 Elm St, City, Country",
    "password": "hashed_password_here"
  }, 
  {
    "firstName": "Liam",
    "lastName": "Baker",
    "phoneNumber": "8901234567",
    "shippingAddress": "456 Oak St, City, Country",
    "billingAddress": "789 Maple St, City, Country",
    "password": "hashed_password_here"
  },
  {
    "firstName": "Ella",
    "lastName": "Gonzalez",
    "phoneNumber": "3456789012",
    "shippingAddress": "789 Elm St, City, Country",
    "billingAddress": "123 Pine St, City, Country",
    "password": "hashed_password_here"
  },
  {
    "firstName": "Jackson",
    "lastName": "Barnes",
    "phoneNumber": "6789012345",
    "shippingAddress": "123 Elm St, City, Country",
    "billingAddress": "456 Oak St, City, Country",
    "password": "hashed_password_here"
  },
  {
    "firstName": "Mia",
    "lastName": "Collins",
    "phoneNumber": "9012345678",
    "shippingAddress": "789 Cedar St, City, Country",
    "billingAddress": "123 Birch St, City, Country",
    "password": "hashed_password_here"
  },
  {
    "firstName": "Aiden",
    "lastName": "Stewart",
    "phoneNumber": "5678901234",
    "shippingAddress": "123 Main St, City, Country",
    "billingAddress": "456 Elm St, City, Country",
    "password": "hashed_password_here"
  }
]